<?xml version="1.0" encoding="UTF-8"?>
<java version="1.8.0_452" class="java.beans.XMLDecoder">
 <object class="model.dto.GymDTO">
  <void property="arenas">
   <object class="java.util.ArrayList">
    <void method="add">
     <object class="model.dto.ArenaDTO">
      <void property="creditsForWinner">
       <int>900</int>
      </void>
      <void property="level">
       <string>EASY</string>
      </void>
      <void property="name">
       <string>arena 1</string>
      </void>
      <void property="type">
       <string>DESERT</string>
      </void>
     </object>
    </void>
    <void method="add">
     <object class="model.dto.ArenaDTO">
      <void property="creditsForWinner">
       <int>960</int>
      </void>
      <void property="level">
       <string>INTERMEDIATE</string>
      </void>
      <void property="name">
       <string>arena 2</string>
      </void>
      <void property="type">
       <string>JUNGLE</string>
      </void>
     </object>
    </void>
   </object>
  </void>
  <void property="trainers">
   <object class="java.util.ArrayList">
    <void method="add">
     <object class="model.dto.TrainerDTO">
      <void property="credits">
       <double>9590.0</double>
      </void>
      <void property="name">
       <string>MILEI</string>
      </void>
      <void property="pokemons">
       <object class="java.util.ArrayList">
        <void method="add">
         <object class="model.dto.PokemonDTO">
          <void property="cost">
           <double>120.0</double>
          </void>
          <void property="name">
           <string>PIKACHU</string>
          </void>
          <void property="type">
           <string>FirePokemon</string>
          </void>
         </object>
        </void>
        <void method="add">
         <object class="model.dto.PokemonDTO">
          <void property="cost">
           <double>100.0</double>
          </void>
          <void property="damage">
           <double>120.0</double>
          </void>
          <void property="health">
           <double>500.0</double>
          </void>
          <void property="name">
           <string>SNORLAX</string>
          </void>
          <void property="shield">
           <double>100.0</double>
          </void>
          <void property="type">
           <string>WaterPokemon</string>
          </void>
          <void property="xp">
           <int>24</int>
          </void>
         </object>
        </void>
       </object>
      </void>
      <void property="weapons">
       <object class="java.util.ArrayList"/>
      </void>
     </object>
    </void>
    <void method="add">
     <object class="model.dto.TrainerDTO">
      <void property="credits">
       <double>7790.0</double>
      </void>
      <void property="name">
       <string>CRISTINA</string>
      </void>
      <void property="pokemons">
       <object class="java.util.ArrayList">
        <void method="add">
         <object class="model.dto.PokemonDTO">
          <void property="cost">
           <double>120.0</double>
          </void>
          <void property="name">
           <string>PIKACHU</string>
          </void>
          <void property="type">
           <string>FirePokemon</string>
          </void>
         </object>
        </void>
        <void method="add">
         <object class="model.dto.PokemonDTO">
          <void property="cost">
           <double>100.0</double>
          </void>
          <void property="damage">
           <double>120.0</double>
          </void>
          <void property="health">
           <double>500.0</double>
          </void>
          <void property="name">
           <string>SNORLAX</string>
          </void>
          <void property="shield">
           <double>100.0</double>
          </void>
          <void property="type">
           <string>WaterPokemon</string>
          </void>
          <void property="xp">
           <int>17</int>
          </void>
         </object>
        </void>
       </object>
      </void>
      <void property="weapons">
       <object class="java.util.ArrayList"/>
      </void>
     </object>
    </void>
    <void method="add">
     <object class="model.dto.TrainerDTO">
      <void property="credits">
       <double>30540.0</double>
      </void>
      <void property="name">
       <string>ALBERTO</string>
      </void>
      <void property="pokemons">
       <object class="java.util.ArrayList">
        <void method="add">
         <object class="model.dto.PokemonDTO">
          <void property="cost">
           <double>120.0</double>
          </void>
          <void property="damage">
           <double>3897.6000000000004</double>
          </void>
          <void property="health">
           <double>25821.600000000002</double>
          </void>
          <void property="name">
           <string>PIKACHU</string>
          </void>
          <void property="shield">
           <double>9744.000000000002</double>
          </void>
          <void property="type">
           <string>FirePokemon</string>
          </void>
          <void property="xp">
           <int>58</int>
          </void>
         </object>
        </void>
        <void method="add">
         <object class="model.dto.PokemonDTO">
          <void property="cost">
           <double>100.0</double>
          </void>
          <void property="damage">
           <double>120.0</double>
          </void>
          <void property="health">
           <double>500.0</double>
          </void>
          <void property="name">
           <string>SNORLAX</string>
          </void>
          <void property="shield">
           <double>100.0</double>
          </void>
          <void property="type">
           <string>WaterPokemon</string>
          </void>
          <void property="xp">
           <int>12</int>
          </void>
         </object>
        </void>
        <void method="add">
         <object class="model.dto.PokemonDTO">
          <void property="cost">
           <double>200.0</double>
          </void>
          <void property="name">
           <string>SNORLAX</string>
          </void>
          <void property="type">
           <string>StonePokemon</string>
          </void>
         </object>
        </void>
       </object>
      </void>
      <void property="weapons">
       <object class="java.util.ArrayList"/>
      </void>
     </object>
    </void>
    <void method="add">
     <object class="model.dto.TrainerDTO">
      <void property="credits">
       <double>2340.0</double>
      </void>
      <void property="name">
       <string>KARINA</string>
      </void>
      <void property="pokemons">
       <object class="java.util.ArrayList">
        <void method="add">
         <object class="model.dto.PokemonDTO">
          <void property="cost">
           <double>120.0</double>
          </void>
          <void property="damage">
           <double>537.6</double>
          </void>
          <void property="health">
           <double>3561.6000000000004</double>
          </void>
          <void property="name">
           <string>PIKACHU</string>
          </void>
          <void property="shield">
           <double>1344.0000000000002</double>
          </void>
          <void property="type">
           <string>FirePokemon</string>
          </void>
          <void property="xp">
           <int>8</int>
          </void>
         </object>
        </void>
       </object>
      </void>
      <void property="weapons">
       <object class="java.util.ArrayList"/>
      </void>
     </object>
    </void>
    <void method="add">
     <object class="model.dto.TrainerDTO">
      <void property="credits">
       <double>16390.0</double>
      </void>
      <void property="name">
       <string>BULRICH</string>
      </void>
      <void property="pokemons">
       <object class="java.util.ArrayList">
        <void method="add">
         <object class="model.dto.PokemonDTO">
          <void property="cost">
           <double>120.0</double>
          </void>
          <void property="damage">
           <double>2553.6000000000004</double>
          </void>
          <void property="health">
           <double>16917.600000000002</double>
          </void>
          <void property="name">
           <string>PIKACHU</string>
          </void>
          <void property="shield">
           <double>6384.0</double>
          </void>
          <void property="type">
           <string>FirePokemon</string>
          </void>
          <void property="xp">
           <int>38</int>
          </void>
         </object>
        </void>
        <void method="add">
         <object class="model.dto.PokemonDTO">
          <void property="cost">
           <double>200.0</double>
          </void>
          <void property="name">
           <string>SNORLAX</string>
          </void>
          <void property="type">
           <string>StonePokemon</string>
          </void>
         </object>
        </void>
       </object>
      </void>
      <void property="weapons">
       <object class="java.util.ArrayList"/>
      </void>
     </object>
    </void>
    <void method="add">
     <object class="model.dto.TrainerDTO">
      <void property="credits">
       <double>7450.0</double>
      </void>
      <void property="name">
       <string>SANTORO</string>
      </void>
      <void property="pokemons">
       <object class="java.util.ArrayList">
        <void method="add">
         <object class="model.dto.PokemonDTO">
          <void property="cost">
           <double>120.0</double>
          </void>
          <void property="damage">
           <double>1612.8000000000002</double>
          </void>
          <void property="health">
           <double>10684.800000000001</double>
          </void>
          <void property="name">
           <string>PIKACHU</string>
          </void>
          <void property="shield">
           <double>4032.000000000001</double>
          </void>
          <void property="type">
           <string>FirePokemon</string>
          </void>
          <void property="xp">
           <int>24</int>
          </void>
         </object>
        </void>
        <void method="add">
         <object class="model.dto.PokemonDTO">
          <void property="cost">
           <double>200.0</double>
          </void>
          <void property="name">
           <string>SNORLAX</string>
          </void>
          <void property="type">
           <string>StonePokemon</string>
          </void>
         </object>
        </void>
       </object>
      </void>
      <void property="weapons">
       <object class="java.util.ArrayList"/>
      </void>
     </object>
    </void>
    <void method="add">
     <object class="model.dto.TrainerDTO">
      <void property="credits">
       <double>380.0</double>
      </void>
      <void property="name">
       <string>GRABOIS</string>
      </void>
      <void property="pokemons">
       <object class="java.util.ArrayList">
        <void method="add">
         <object class="model.dto.PokemonDTO">
          <void property="cost">
           <double>120.0</double>
          </void>
          <void property="name">
           <string>PIKACHU</string>
          </void>
          <void property="type">
           <string>FirePokemon</string>
          </void>
         </object>
        </void>
        <void method="add">
         <object class="model.dto.PokemonDTO">
          <void property="cost">
           <double>100.0</double>
          </void>
          <void property="damage">
           <double>431.1752612297673</double>
          </void>
          <void property="health">
           <double>200.0</double>
          </void>
          <void property="name">
           <string>SNORLAX</string>
          </void>
          <void property="shield">
           <double>100.0</double>
          </void>
          <void property="type">
           <string>IcePokemon</string>
          </void>
          <void property="xp">
           <int>1</int>
          </void>
         </object>
        </void>
       </object>
      </void>
      <void property="weapons">
       <object class="java.util.ArrayList"/>
      </void>
     </object>
    </void>
    <void method="add">
     <object class="model.dto.TrainerDTO">
      <void property="credits">
       <double>4100.0</double>
      </void>
      <void property="name">
       <string>NESTOR</string>
      </void>
      <void property="pokemons">
       <object class="java.util.ArrayList">
        <void method="add">
         <object class="model.dto.PokemonDTO">
          <void property="cost">
           <double>120.0</double>
          </void>
          <void property="name">
           <string>PIKACHU</string>
          </void>
          <void property="type">
           <string>FirePokemon</string>
          </void>
         </object>
        </void>
        <void method="add">
         <object class="model.dto.PokemonDTO">
          <void property="cost">
           <double>100.0</double>
          </void>
          <void property="damage">
           <double>601.642437085219</double>
          </void>
          <void property="health">
           <double>200.0</double>
          </void>
          <void property="name">
           <string>SNORLAX</string>
          </void>
          <void property="shield">
           <double>100.0</double>
          </void>
          <void property="type">
           <string>IcePokemon</string>
          </void>
          <void property="xp">
           <int>6</int>
          </void>
         </object>
        </void>
       </object>
      </void>
      <void property="weapons">
       <object class="java.util.ArrayList"/>
      </void>
     </object>
    </void>
   </object>
  </void>
 </object>
</java>
